[{"sura":106,"aya":1,"quran_text":"بِسْمِ اللَّهِ الرَّحْمَنِ الرَّحِيمِ لِإِيلَافِ قُرَيْشٍ","bangla_text":"কোরাইশের আসক্তির কারণে,","english_text":"SINCE THE QURAISH have been united,","bangla_translit":"লিঈলা-ফি কুরইশিন্।","english_translit":"Lieelafi qurayshin"},{"sura":106,"aya":2,"quran_text":"إِيلَافِهِمْ رِحْلَةَ الشِّتَاءِ وَالصَّيْفِ","bangla_text":"আসক্তির কারণে তাদের শীত ও গ্রীষ্মকালীন সফরের।","english_text":"United to fit out caravans winter and summer,","bangla_translit":"ঈলা-ফিহিম্ রিহ্লাতাশ্ শিতা-য়ি অছ্ছোয়াইফ্।","english_translit":"Eelafihim rihlata alshshitai waalssayfi"},{"sura":106,"aya":3,"quran_text":"فَلْيَعْبُدُوا رَبَّ هَذَا الْبَيْتِ","bangla_text":"অতএব তারা যেন এবাদত করে এই ঘরের পালনকর্তার","english_text":"Let them worship the Lord of this House,","bangla_translit":"ফাল্ইয়া’বুদূ রব্বাহা-যাল্ বাইতি","english_translit":"FalyaAAbudoo rabba hatha albayti"},{"sura":106,"aya":4,"quran_text":"الَّذِي أَطْعَمَهُمْ مِنْ جُوعٍ وَآمَنَهُمْ مِنْ خَوْفٍ","bangla_text":"যিনি তাদেরকে ক্ষুধায় আহার দিয়েছেন এবং যুদ্ধভীতি থেকে তাদেরকে নিরাপদ করেছেন।","english_text":"Who provided them against destitution and gave them security against fear.","bangla_translit":"ল্লাযী আত্ব‘আমাহুম্ মিন্ জুইঁও ওয়া আ-মানাহুম্ মিন্ খাওফ্।","english_translit":"Allathee atAAamahum min jooAAin waamanahum min khawfin"}]