[{"sura":85,"aya":1,"quran_text":"بِسْمِ اللَّهِ الرَّحْمَنِ الرَّحِيمِ وَالسَّمَاءِ ذَاتِ الْبُرُوجِ","bangla_text":"শপথ গ্রহ-নক্ষত্র শোভিত আকাশের,","english_text":"I CALL TO witness the sky (bespangled) with the signs of the Zodiac,","bangla_translit":"অস্সামা-য়ি যা-তিল্ বুরূজ্বি","english_translit":null},{"sura":85,"aya":2,"quran_text":"وَالْيَوْمِ الْمَوْعُودِ","bangla_text":"এবং প্রতিশ্রুত দিবসের,","english_text":"And the promised day,","bangla_translit":"অল্ইয়াওমিল্ মাও‘ঊদি।","english_translit":null},{"sura":85,"aya":3,"quran_text":"وَشَاهِدٍ وَمَشْهُودٍ","bangla_text":"এবং সেই দিবসের, যে উপস্থিত হয় ও যাতে উপস্থিত হয়","english_text":"And the witness and the witnessed,","bangla_translit":"অশা-হিদিঁও অমাশ্হূদ্।","english_translit":null},{"sura":85,"aya":4,"quran_text":"قُتِلَ أَصْحَابُ الْأُخْدُودِ","bangla_text":"অভিশপ্ত হয়েছে গর্ত ওয়ালারা অর্থাৎ,","english_text":"That accursed are the men of the trench","bangla_translit":"কুতিলা আছ্হা-বুল্ উখ্দূদি।","english_translit":null},{"sura":85,"aya":5,"quran_text":"النَّارِ ذَاتِ الْوَقُودِ","bangla_text":"অনেক ইন্ধনের অগ্নিসংযোগকারীরা;","english_text":"Full of fire fed by faggots,","bangla_translit":"আন্না-রি যা-তিল্ অকুদি","english_translit":null},{"sura":85,"aya":6,"quran_text":"إِذْ هُمْ عَلَيْهَا قُعُودٌ","bangla_text":"যখন তারা তার কিনারায় বসেছিল।","english_text":"As they sat around it","bangla_translit":"ইয্হুম্ ‘আলাইহা-কুঊ’দুঁও।","english_translit":null},{"sura":85,"aya":7,"quran_text":"وَهُمْ عَلَى مَا يَفْعَلُونَ بِالْمُؤْمِنِينَ شُهُودٌ","bangla_text":"এবং তারা বিশ্বাসীদের সাথে যা করেছিল, তা নিরীক্ষণ করছিল।","english_text":"Witnessing what they had done to the believers!","bangla_translit":"অহুম্ ‘আলা-মা-ইয়াফ্‘আলূনা বিল্মুমিনীনা শুহূদ্।","english_translit":null},{"sura":85,"aya":8,"quran_text":"وَمَا نَقَمُوا مِنْهُمْ إِلَّا أَنْ يُؤْمِنُوا بِاللَّهِ الْعَزِيزِ الْحَمِيدِ","bangla_text":"তারা তাদেরকে শাস্তি দিয়েছিল শুধু এ কারণে যে, তারা প্রশংসিত, পরাক্রান্ত আল্লাহর প্রতি বিশ্বাস স্থাপন করেছিল,","english_text":"They had no other reason for hating them except that they believed in God the mighty, worthy of praise,","bangla_translit":"অমা-নাক্বমূ মিন্হুম্ ইল্লা য় আইঁ ইয়ুমিনূ বিল্লা-হিল্ ‘আযীযিল্ হামীদি।","english_translit":null},{"sura":85,"aya":9,"quran_text":"الَّذِي لَهُ مُلْكُ السَّمَاوَاتِ وَالْأَرْضِ وَاللَّهُ عَلَى كُلِّ شَيْءٍ شَهِيدٌ","bangla_text":"যিনি নভোমন্ডল ও ভূমন্ডলের ক্ষমতার মালিক, আল্লাহর সামনে রয়েছে সবকিছু।","english_text":"Whose kingdom spreads over the heavens and the earth. God is witness over everything.","bangla_translit":"ল্লাযী লাহূ মুল্কুস্ সামা-ওয়া-তি অল্ র্আদ্ব; অল্লা-হু ‘আলা- কুল্লি শাইয়িন্ শাহীদ্।","english_translit":null},{"sura":85,"aya":10,"quran_text":"إِنَّ الَّذِينَ فَتَنُوا الْمُؤْمِنِينَ وَالْمُؤْمِنَاتِ ثُمَّ لَمْ يَتُوبُوا فَلَهُمْ عَذَابُ جَهَنَّمَ وَلَهُمْ عَذَابُ الْحَرِيقِ","bangla_text":"যারা মুমিন পুরুষ ও নারীকে নিপীড়ন করেছে, অতঃপর তওবা করেনি, তাদের জন্যে আছে জাহান্নামের শাস্তি, আর আছে দহন যন্ত্রণা,","english_text":"Surely for those who persecute believers, men and women, and do not repent afterwards, is the punishment of Hell, and the punishment of burning.","bangla_translit":"ইন্নাল্লাযীনা ফাতানুল্ মুমিনীনা অল্মুমিনা-তি ছুম্মা লাম্ ইয়াতূবূ ফালাহুম্ ‘আযা-বু জ্বাহান্নামাঅলাহুম্ ‘আযা-বুল্ হারীক্ব্।","english_translit":null},{"sura":85,"aya":11,"quran_text":"إِنَّ الَّذِينَ آمَنُوا وَعَمِلُوا الصَّالِحَاتِ لَهُمْ جَنَّاتٌ تَجْرِي مِنْ تَحْتِهَا الْأَنْهَارُ ذَلِكَ الْفَوْزُ الْكَبِيرُ","bangla_text":"যারা ঈমান আনে ও সৎকর্ম করে তাদের জন্যে আছে জান্নাত, যার তলদেশে প্রবাহিত হয় নির্ঝরিণীসমূহ। এটাই মহাসাফল্য।","english_text":"Surely for those who believe and do the right are gardens with rivers running by. That is the greatest success.","bangla_translit":"ইন্নাল্লাযীনা আ-মানূ অ‘আমিলুছ্ ছোয়া-লিহা-তি লাহুম্ জ্বান্না-তুন্ তাজরী মিন্ তাহ্তিহাল্ আন্হার্-; যা-লিকাল্ ফাওযুল্ কার্বী।","english_translit":null},{"sura":85,"aya":12,"quran_text":"إِنَّ بَطْشَ رَبِّكَ لَشَدِيدٌ","bangla_text":"নিশ্চয় তোমার পালনকর্তার পাকড়াও অত্যন্ত কঠিন।","english_text":"The grip of your Lord is severe indeed!","bangla_translit":"ইন্না বাতশা রব্বিকা লাশাদীদ্।","english_translit":null},{"sura":85,"aya":13,"quran_text":"إِنَّهُ هُوَ يُبْدِئُ وَيُعِيدُ","bangla_text":"তিনিই প্রথমবার অস্তিত্ব দান করেন এবং পুনরায় জীবিত করেন।","english_text":"It is verily He who initiates and repeats.","bangla_translit":"ইন্নাহূ হুওয়া ইয়ুব্দিয়ু অইয়ু‘ঈদ্।","english_translit":null},{"sura":85,"aya":14,"quran_text":"وَهُوَ الْغَفُورُ الْوَدُودُ","bangla_text":"তিনি ক্ষমাশীল, প্রেমময়;","english_text":"He is the forgiving and the loving,","bangla_translit":"অহুওয়াল্ গফূরুল্ ওয়াদূদু","english_translit":null},{"sura":85,"aya":15,"quran_text":"ذُو الْعَرْشِ الْمَجِيدُ","bangla_text":"মহান আরশের অধিকারী।","english_text":"The Lord of the glorious Throne,","bangla_translit":"যুল্ ‘র্আশিল্ মাজ্বীদু","english_translit":null},{"sura":85,"aya":16,"quran_text":"فَعَّالٌ لِمَا يُرِيدُ","bangla_text":"তিনি যা চান, তাই করেন।","english_text":"Who does as He pleases.","bangla_translit":"ফা’আ’লুল্ লিমা- ইয়ুরীদ্।","english_translit":null},{"sura":85,"aya":17,"quran_text":"هَلْ أَتَاكَ حَدِيثُ الْجُنُودِ","bangla_text":"আপনার কাছে সৈন্যবাহিনীর ইতিবৃত্ত পৌছেছে কি?","english_text":"Has the story of the hordes","bangla_translit":"হাল্ আতা-কা হাদীছুল্ জুনূ দি","english_translit":null},{"sura":85,"aya":18,"quran_text":"فِرْعَوْنَ وَثَمُودَ","bangla_text":"ফেরাউনের এবং সামুদের?","english_text":"Of Pharaoh and Thamud come to you?","bangla_translit":"র্ফি‘আউনা অছামূদ্।","english_translit":null},{"sura":85,"aya":19,"quran_text":"بَلِ الَّذِينَ كَفَرُوا فِي تَكْذِيبٍ","bangla_text":"বরং যারা কাফের, তারা মিথ্যারোপে রত আছে।","english_text":"Yet the infidels persist in denial.","bangla_translit":"বালিল্লাযীনা কাফারূ ফী তাক্যীবিঁও","english_translit":null},{"sura":85,"aya":20,"quran_text":"وَاللَّهُ مِنْ وَرَائِهِمْ مُحِيطٌ","bangla_text":"আল্লাহ তাদেরকে চতুর্দিক থেকে পরিবেষ্টন করে রেখেছেন।","english_text":"But God surrounds them from all sides.","bangla_translit":"অল্লা-হু মিওঁ অরা য় য়িহিম্ মুহীত্ব্।","english_translit":null},{"sura":85,"aya":21,"quran_text":"بَلْ هُوَ قُرْآنٌ مَجِيدٌ","bangla_text":"বরং এটা মহান কোরআন,","english_text":"This is indeed the glorious Qur'an","bangla_translit":"বাল্ হুওয়া কুরআ-নুম্ মাজ্বীদুন্","english_translit":null},{"sura":85,"aya":22,"quran_text":"فِي لَوْحٍ مَحْفُوظٍ","bangla_text":"লওহে মাহফুযে লিপিবদ্ধ।","english_text":"(Preserved) on the guarded tablet.","bangla_translit":"ফী লাওহিম্ মাহ্ফূজ্","english_translit":null}]